{
"type": "FeatureCollection",
"name": "layer_消防單位",
"crs": { "type": "name", "properties": { "name": "urn:ogc:def:crs:OGC:1.3:CRS84" } },
"xy_coordinate_resolution": 1e-15,
"features": [
{ "type": "Feature", "properties": { "單位別": "嘉義市政府消防局", "地址": "嘉義市立學街16號", "電話": "05-2716660", "經度": 120.467217, "緯度": 23.4723377, "layer": "消防單位", "path": "Point?crs=EPSG:3824&field=%E5%96%AE%E4%BD%8D%E5%88%A5:string(254,0)&field=%E5%9C%B0%E5%9D%80:string(254,0)&field=%E9%9B%BB%E8%A9%B1:string(254,0)&field=%E7%B6%93%E5%BA%A6:double(23,15)&field=%E7%B7%AF%E5%BA%A6:double(23,15)&uid={8b6377c0-4c87-4381-a858-5", "BOOLEAN": false }, "geometry": { "type": "Point", "coordinates": [ 120.467217, 23.4723377 ] } },
{ "type": "Feature", "properties": { "單位別": "湖內分隊", "地址": "嘉義市南京路59號", "電話": "05-2832051", "經度": 120.4411167, "緯度": 23.4561649, "layer": "消防單位", "path": "Point?crs=EPSG:3824&field=%E5%96%AE%E4%BD%8D%E5%88%A5:string(254,0)&field=%E5%9C%B0%E5%9D%80:string(254,0)&field=%E9%9B%BB%E8%A9%B1:string(254,0)&field=%E7%B6%93%E5%BA%A6:double(23,15)&field=%E7%B7%AF%E5%BA%A6:double(23,15)&uid={8b6377c0-4c87-4381-a858-5", "BOOLEAN": false }, "geometry": { "type": "Point", "coordinates": [ 120.441116699999981, 23.4561649 ] } },
{ "type": "Feature", "properties": { "單位別": "蘭潭分隊", "地址": "嘉義市立學街16號", "電話": "05-2715390", "經度": 120.467217, "緯度": 23.4723377, "layer": "消防單位", "path": "Point?crs=EPSG:3824&field=%E5%96%AE%E4%BD%8D%E5%88%A5:string(254,0)&field=%E5%9C%B0%E5%9D%80:string(254,0)&field=%E9%9B%BB%E8%A9%B1:string(254,0)&field=%E7%B6%93%E5%BA%A6:double(23,15)&field=%E7%B7%AF%E5%BA%A6:double(23,15)&uid={8b6377c0-4c87-4381-a858-5", "BOOLEAN": false }, "geometry": { "type": "Point", "coordinates": [ 120.467217, 23.4723377 ] } }
]
}
